Metadata-Version: 2.1
Name: shytools
Version: 1.0.1
Summary: Shy tools.
Home-page: UNKNOWN
Author: José Falero
Author-email: jzfalero@gmail.com
License: GPLv3+
Keywords: private attribute
Platform: UNKNOWN
Classifier: Programming Language :: Python :: 3
Classifier: Development Status :: 5 - Production/Stable
Classifier: Intended Audience :: Developers
Classifier: License :: OSI Approved :: GNU General Public License v3 or later (GPLv3+)
Classifier: Operating System :: OS Independent
Classifier: Topic :: Software Development :: Libraries
Requires-Python: >=3.6
